{"nodes":[{"id":"cornerstone_committees","label":"CornerstoneCommittees","file_type":"code","source_file":"src/app/components/CornerstoneCommittees.tsx"},{"id":"events","label":"Events","file_type":"code","source_file":"src/app/components/Events.tsx"},{"id":"footer","label":"Footer","file_type":"code","source_file":"src/app/components/Footer.tsx"},{"id":"hero","label":"Hero","file_type":"code","source_file":"src/app/components/Hero.tsx"},{"id":"ieee_purdue_logo","label":"IeeePurdueLogo","file_type":"code","source_file":"src/app/components/IeeePurdueLogo.tsx"},{"id":"join_cta","label":"JoinCTA","file_type":"code","source_file":"src/app/components/JoinCTA.tsx"},{"id":"layout","label":"Layout","file_type":"code","source_file":"src/app/components/Layout.tsx"},{"id":"magnetic_button","label":"MagneticButton","file_type":"code","source_file":"src/app/components/MagneticButton.tsx"},{"id":"navigation","label":"Navigation","file_type":"code","source_file":"src/app/components/Navigation.tsx"},{"id":"page_transition","label":"PageTransition","file_type":"code","source_file":"src/app/components/PageTransition.tsx"},{"id":"stats","label":"Stats","file_type":"code","source_file":"src/app/components/Stats.tsx"},{"id":"tech_marquee","label":"TechMarquee","file_type":"code","source_file":"src/app/components/TechMarquee.tsx"},{"id":"theme_toggle","label":"ThemeToggle","file_type":"code","source_file":"src/app/components/ThemeToggle.tsx"},{"id":"ux_effects","label":"UXEffects","file_type":"code","source_file":"src/app/components/UXEffects.tsx"},{"id":"image_with_fallback","label":"ImageWithFallback","file_type":"code","source_file":"src/app/components/figma/ImageWithFallback.tsx"},{"id":"ui_accordion","label":"Accordion","file_type":"code","source_file":"src/app/components/ui/accordion.tsx"},{"id":"ui_alert_dialog","label":"AlertDialog","file_type":"code","source_file":"src/app/components/ui/alert-dialog.tsx"},{"id":"ui_alert","label":"Alert","file_type":"code","source_file":"src/app/components/ui/alert.tsx"},{"id":"ui_aspect_ratio","label":"AspectRatio","file_type":"code","source_file":"src/app/components/ui/aspect-ratio.tsx"},{"id":"ui_avatar","label":"Avatar","file_type":"code","source_file":"src/app/components/ui/avatar.tsx"},{"id":"ui_badge","label":"Badge","file_type":"code","source_file":"src/app/components/ui/badge.tsx"}],"edges":[{"source":"cornerstone_committees","target":"use_cornerstone_committees","relation":"calls","confidence":"EXTRACTED","confidence_score":1.0, "source_file":"src/app/components/CornerstoneCommittees.tsx"},{"source":"events","target":"use_google_calendar_events","relation":"calls","confidence":"EXTRACTED","confidence_score":1.0, "source_file":"src/app/components/Events.tsx"},{"source":"footer","target":"ieee_purdue_logo","relation":"references","confidence":"EXTRACTED","confidence_score":1.0, "source_file":"src/app/components/Footer.tsx"},{"source":"footer","target":"magnetic_wrapper","relation":"references","confidence":"EXTRACTED","confidence_score":1.0, "source_file":"src/app/components/Footer.tsx"},{"source":"hero","target":"use_home_page","relation":"calls","confidence":"EXTRACTED","confidence_score":1.0, "source_file":"src/app/components/Hero.tsx"},{"source":"hero","target":"magnetic_button","relation":"references","confidence":"EXTRACTED","confidence_score":1.0, "source_file":"src/app/components/Hero.tsx"},{"source":"join_cta","target":"magnetic_button","relation":"references","confidence":"EXTRACTED","confidence_score":1.0, "source_file":"src/app/components/JoinCTA.tsx"},{"source":"layout","target":"navigation","relation":"references","confidence":"EXTRACTED","confidence_score":1.0, "source_file":"src/app/components/Layout.tsx"},{"source":"layout","target":"footer","relation":"references","confidence":"EXTRACTED","confidence_score":1.0, "source_file":"src/app/components/Layout.tsx"},{"source":"navigation","target":"ieee_purdue_logo","relation":"references","confidence":"EXTRACTED","confidence_score":1.0, "source_file":"src/app/components/Navigation.tsx"},{"source":"navigation","target":"theme_toggle","relation":"references","confidence":"EXTRACTED","confidence_score":1.0, "source_file":"src/app/components/Navigation.tsx"},{"source":"navigation","target":"magnetic_button","relation":"references","confidence":"EXTRACTED","confidence_score":1.0, "source_file":"src/app/components/Navigation.tsx"},{"source":"stats","target":"use_count_up","relation":"calls","confidence":"EXTRACTED","confidence_score":1.0, "source_file":"src/app/components/Stats.tsx"},{"source":"tech_marquee","target":"use_partners","relation":"calls","confidence":"EXTRACTED","confidence_score":1.0, "source_file":"src/app/components/TechMarquee.tsx"},{"source":"magnetic_button","target":"magnetic_wrapper","relation":"semantically_similar_to","confidence":"INFERRED","confidence_score":0.9, "source_file":"src/app/components/MagneticButton.tsx"},{"source":"ux_effects","target":"magnetic_button","relation":"conceptually_related_to","confidence":"INFERRED","confidence_score":0.75, "source_file":"src/app/components/UXEffects.tsx"}],"hyperedges":[{"id":"ui_primitives_shadcn","label":"Radix-based UI Primitives","nodes":["ui_accordion","ui_alert_dialog","ui_alert","ui_aspect_ratio","ui_avatar","ui_badge"],"relation":"implement","confidence":"EXTRACTED","confidence_score":1.0, "source_file":"src/app/components/ui/accordion.tsx"},{"id":"home_page_sections","label":"Home Page Core Sections","nodes":["hero","cornerstone_committees","events","join_cta","stats","tech_marquee"],"relation":"form","confidence":"INFERRED","confidence_score":0.95, "source_file":"src/app/components/Hero.tsx"},{"id":"motion_enhanced_ux","label":"Interactive Motion System","nodes":["magnetic_button","page_transition","ux_effects"],"relation":"participate_in","confidence":"INFERRED","confidence_score":0.9, "source_file":"src/app/components/UXEffects.tsx"}],"input_tokens":0,"output_tokens":0}