{
  "breakpoints": {
    "375": {
      "name": "committee-content",
      "viewportWidth": 311,
      "width": 311,
      "height": 560,
      "bones": [
        [
          0,
          0,
          100,
          17,
          8
        ],
        [
          0,
          37,
          100,
          392,
          4,
          true
        ],
        [
          10.6109,
          70,
          78.7781,
          326,
          8
        ],
        [
          0,
          492,
          41.1324,
          30,
          2
        ],
        [
          43.7048,
          492,
          29.4313,
          30,
          2
        ],
        [
          0,
          530,
          24.7488,
          30,
          2
        ],
        [
          27.3211,
          530,
          17.7251,
          30,
          2
        ]
      ]
    },
    "640": {
      "name": "committee-content",
      "viewportWidth": 576,
      "width": 576,
      "height": 344,
      "bones": [
        [
          0,
          0,
          100,
          17,
          8
        ],
        [
          0,
          37,
          100,
          214,
          4,
          true
        ],
        [
          5.7292,
          70,
          88.5417,
          148,
          8
        ],
        [
          0,
          315,
          22.2087,
          30,
          2
        ],
        [
          23.5975,
          315,
          15.8908,
          30,
          2
        ],
        [
          40.8773,
          315,
          13.3626,
          30,
          2
        ],
        [
          55.6288,
          315,
          9.5703,
          30,
          2
        ]
      ]
    },
    "768": {
      "name": "committee-content",
      "viewportWidth": 704,
      "width": 704,
      "height": 315,
      "bones": [
        [
          0,
          0,
          100,
          17,
          8
        ],
        [
          0,
          37,
          100,
          184,
          4,
          true
        ],
        [
          4.6875,
          70,
          90.625,
          118,
          8
        ],
        [
          0,
          285,
          18.1707,
          30,
          2
        ],
        [
          19.3071,
          285,
          13.0016,
          30,
          2
        ],
        [
          33.445,
          285,
          10.9331,
          30,
          2
        ],
        [
          45.5145,
          285,
          7.8303,
          30,
          2
        ]
      ]
    },
    "1024": {
      "name": "committee-content",
      "viewportWidth": 532,
      "width": 532,
      "height": 374,
      "bones": [
        [
          0,
          0,
          100,
          17,
          8
        ],
        [
          0,
          37,
          100,
          244,
          4,
          true
        ],
        [
          6.203,
          70,
          87.594,
          178,
          8
        ],
        [
          0,
          344,
          24.0455,
          30,
          2
        ],
        [
          25.5492,
          344,
          17.2051,
          30,
          2
        ],
        [
          44.2581,
          344,
          14.4678,
          30,
          2
        ],
        [
          60.2297,
          344,
          10.3618,
          30,
          2
        ]
      ]
    },
    "1280": {
      "name": "committee-content",
      "viewportWidth": 788,
      "width": 788,
      "height": 315,
      "bones": [
        [
          0,
          0,
          100,
          17,
          8
        ],
        [
          0,
          37,
          100,
          184,
          4,
          true
        ],
        [
          4.1878,
          70,
          91.6244,
          118,
          8
        ],
        [
          0,
          285,
          16.2337,
          30,
          2
        ],
        [
          17.249,
          285,
          11.6156,
          30,
          2
        ],
        [
          29.8798,
          285,
          9.7676,
          30,
          2
        ],
        [
          40.6627,
          285,
          6.9956,
          30,
          2
        ]
      ]
    },
    "1536": {
      "name": "committee-content",
      "viewportWidth": 788,
      "width": 788,
      "height": 315,
      "bones": [
        [
          0,
          0,
          100,
          17,
          8
        ],
        [
          0,
          37,
          100,
          184,
          4,
          true
        ],
        [
          4.1878,
          70,
          91.6244,
          118,
          8
        ],
        [
          0,
          285,
          16.2337,
          30,
          2
        ],
        [
          17.249,
          285,
          11.6156,
          30,
          2
        ],
        [
          29.8798,
          285,
          9.7676,
          30,
          2
        ],
        [
          40.6627,
          285,
          6.9956,
          30,
          2
        ]
      ]
    }
  },
  "_hash": "ea41abcdece1b5e69e9e75cb8527537f"
}